Workbook
Name Slicer_ad_group_simplified: #N/A
Name Slicer_Month: #N/A

Sheet new dashboard
R6: Total Sales | T6: Total Cost
R7: =GETPIVOTDATA("Sum of Sale Amount",kpis!$A$3) -> 12049074 | T7: =GETPIVOTDATA("Sum of Cost",kpis!$A$3) -> 635372
R9: Converstion Rate | T9: Cost per Conversion
R10: =IF(GETPIVOTDATA("Sum of Clicks",kpis!$A$3)=0,0,GETPIVOTDATA("Sum of Conversions",kpis!$A$3)/GETPIVOTDATA("Sum of Clicks",kpis!$A$3)) -> 0.10383525 | T10: =IF(GETPIVOTDATA("Sum of Conversions",kpis!$A$3)=0,0,GETPIVOTDATA("Sum of Cost",kpis!$A$3)/GETPIVOTDATA("Sum of Conversions",kpis!$A$3)) -> 6.6187341
R12: Net Profit or Loss | T12: ROAS
R13: =GETPIVOTDATA("Sum of P&L",kpis!$A$3) -> -73408.764 | T13: =IF(GETPIVOTDATA("Sum of Cost",kpis!$A$3)=0,0,GETPIVOTDATA("Sum of Sale Amount",kpis!$A$3)/GETPIVOTDATA("Sum of Cost",kpis!$A$3)) -> 18.963811

Sheet kpis
A3: Sum of Impressions | B3: Sum of Clicks | C3: Sum of Conversions | D3: Sum of Cost | E3: Sum of Sale Amount | F3: Sum of P&L
A4: 2674699 | B4: 924503 | C4: 95996 | D4: 635372 | E4: 12049074 | F4: -73408.764

Sheet sale trend
A3: Row Labels | B3: Sum of Sale Amount
A4: July | B4: 2148710.3
A5: August | B5: 1605066
A6: September | B6: 1319949.1
A7: October | B7: 1676593.5
A8: November | B8: 5298755.4
A9: Grand Total | B9: 12049074

Sheet p&l of adgroup
A3: Row Labels | B3: Sum of P&L
A4: Exact Desk | B4: -3494.846
A5: Phrase Desk | B5: -4021.733
A6: Exact Mob | B6: -8524.582
A7: Phrase Mob | B7: -8618.359
A8: 1:1 Desk | B8: -20490.74
A9: 1:1 Mob | B9: -28258.504
A10: Grand Total | B10: -73408.764

Sheet sale by adgroup
A3: Row Labels | B3: Sum of Sale Amount
A4: 1:1 Desk | B4: 3897156.7
A5: 1:1 Mob | B5: 4923511
A6: Exact Desk | B6: 979856.13
A7: Exact Mob | B7: 1064887.6
A8: Phrase Desk | B8: 698423.61
A9: Phrase Mob | B9: 485239.21
A10: Grand Total | B10: 12049074

Sheet Sheet5
A3: Row Labels | B3: Sum of Cost | C3: Sum of Sale Amount
A4: July | B4: 120541 | C4: 2148710.3
A5: August | B5: 84225 | C5: 1605066
A6: September | B6: 71597 | C6: 1319949.1
A7: October | B7: 78256 | C7: 1676593.5
A8: November | B8: 280753 | C8: 5298755.4
A9: Grand Total | B9: 635372 | C9: 12049074

Sheet final_shop_6modata
A1: Ad Group | B1: Month | C1: Impressions | D1: Clicks | E1: CTR | F1: Conversions | G1: Conv Rate | H1: Cost | I1: CPC | J1: Revenue | K1: Sale Amount | L1: P&L | M1: ad group simplified
A2: Shop - 1:1 - Desk - [shop coupon code] | B2: July | C2: 16038 | D2: 6504 | E2: 0.41 | F2: 1166 | G2: 0.1 | H2: 6669 | I2: 1.03 | J2: 6402 | K2: 136770.05 | L2: -267.086 | M2: =IFERROR( IF(AND(ISNUMBER(SEARCH("1:1", A2)), ISNUMBER(SEARCH("Desk", A2))), "1:1 Desk", IF(AND(ISNUMBER(SEARCH("1:1", A2)), ISNUMBER(SEARCH("Mob", A2))), "1:1 Mob", IF(AND(ISNUMBER(SEARCH("Exact", A2)), ISNUMBER(SEARCH("Desk", A2))), "Exact Desk", IF(AND(ISNUMBER(SEARCH("Exact", A2)), ISNUMBER(SEARCH("Mob", A2))), "Exact Mob", IF(AND(ISNUMBER(SEARCH("Phrase", A2)), ISNUMBER(SEARCH("Desk", A2))), "Phrase Desk", IF(AND(ISNUMBER(SEARCH("Phrase", A2)), ISNUMBER(SEARCH("Mob", A2))), "Phrase Mob", "Other")))))), "Other") -> 1:1 Desk
A3: Shop - 1:1 - Desk - [shop coupon] | B3: July | C3: 36462 | D3: 14367 | E3: 0.39 | F3: 2188 | G3: 0.09 | H3: 13746 | I3: 0.96 | J3: 13262 | K3: 283215.21 | L3: -483.951 | M3: =IFERROR( IF(AND(ISNUMBER(SEARCH("1:1", A3)), ISNUMBER(SEARCH("Desk", A3))), "1:1 Desk", IF(AND(ISNUMBER(SEARCH("1:1", A3)), ISNUMBER(SEARCH("Mob", A3))), "1:1 Mob", IF(AND(ISNUMBER(SEARCH("Exact", A3)), ISNUMBER(SEARCH("Desk", A3))), "Exact Desk", IF(AND(ISNUMBER(SEARCH("Exact", A3)), ISNUMBER(SEARCH("Mob", A3))), "Exact Mob", IF(AND(ISNUMBER(SEARCH("Phrase", A3)), ISNUMBER(SEARCH("Desk", A3))), "Phrase Desk", IF(AND(ISNUMBER(SEARCH("Phrase", A3)), ISNUMBER(SEARCH("Mob", A3))), "Phrase Mob", "Other")))))), "Other") -> 1:1 Desk
A4: Shop - 1:1 - Desk - [shop discount code] | B4: July | C4: 3635 | D4: 1458 | E4: 0.4 | F4: 248 | G4: 0.09 | H4: 1606 | I4: 1.1 | J4: 1723 | K4: 39165.46 | L4: 117.136 | M4: =IFERROR( IF(AND(ISNUMBER(SEARCH("1:1", A4)), ISNUMBER(SEARCH("Desk", A4))), "1:1 Desk", IF(AND(ISNUMBER(SEARCH("1:1", A4)), ISNUMBER(SEARCH("Mob", A4))), "1:1 Mob", IF(AND(ISNUMBER(SEARCH("Exact", A4)), ISNUMBER(SEARCH("Desk", A4))), "Exact Desk", IF(AND(ISNUMBER(SEARCH("Exact", A4)), ISNUMBER(SEARCH("Mob", A4))), "Exact Mob", IF(AND(ISNUMBER(SEARCH("Phrase", A4)), ISNUMBER(SEARCH("Desk", A4))), "Phrase Desk", IF(AND(ISNUMBER(SEARCH("Phrase", A4)), ISNUMBER(SEARCH("Mob", A4))), "Phrase Mob", "Other")))))), "Other") -> 1:1 Desk
A5: Shop - 1:1 - Desk - [shop promo code] | B5: July | C5: 26185 | D5: 10418 | E5: 0.4 | F5: 2294 | G5: 0.12 | H5: 13278 | I5: 1.27 | J5: 13042 | K5: 284823.48 | L5: -235.921 | M5: =IFERROR( IF(AND(ISNUMBER(SEARCH("1:1", A5)), ISNUMBER(SEARCH("Desk", A5))), "1:1 Desk", IF(AND(ISNUMBER(SEARCH("1:1", A5)), ISNUMBER(SEARCH("Mob", A5))), "1:1 Mob", IF(AND(ISNUMBER(SEARCH("Exact", A5)), ISNUMBER(SEARCH("Desk", A5))), "Exact Desk", IF(AND(ISNUMBER(SEARCH("Exact", A5)), ISNUMBER(SEARCH("Mob", A5))), "Exact Mob", IF(AND(ISNUMBER(SEARCH("Phrase", A5)), ISNUMBER(SEARCH("Desk", A5))), "Phrase Desk", IF(AND(ISNUMBER(SEARCH("Phrase", A5)), ISNUMBER(SEARCH("Mob", A5))), "Phrase Mob", "Other")))))), "Other") -> 1:1 Desk
A6: Shop - 1:1 - Desk - [shop promo] | B6: July | C6: 808 | D6: 282 | E6: 0.35 | F6: 61 | G6: 0.15 | H6: 391 | I6: 1.39 | J6: 337 | K6: 7717.77 | L6: -53.604 | M6: =IFERROR( IF(AND(ISNUMBER(SEARCH("1:1", A6)), ISNUMBER(SEARCH("Desk", A6))), "1:1 Desk", IF(AND(ISNUMBER(SEARCH("1:1", A6)), ISNUMBER(SEARCH("Mob", A6))), "1:1 Mob", IF(AND(ISNUMBER(SEARCH("Exact", A6)), ISNUMBER(SEARCH("Desk", A6))), "Exact Desk", IF(AND(ISNUMBER(SEARCH("Exact", A6)), ISNUMBER(SEARCH("Mob", A6))), "Exact Mob", IF(AND(ISNUMBER(SEARCH("Phrase", A6)), ISNUMBER(SEARCH("Desk", A6))), "Phrase Desk", IF(AND(ISNUMBER(SEARCH("Phrase", A6)), ISNUMBER(SEARCH("Mob", A6))), "Phrase Mob", "Other")))))), "Other") -> 1:1 Desk
A7: Shop - 1:1 - Mob - [shop coupon code] | B7: July | C7: 46507 | D7: 21756 | E7: 0.47 | F7: 1665 | G7: 0.05 | H7: 13157 | I7: 0.6 | J7: 8550 | K7: 185824.49 | L7: -4606.713 | M7: =IFERROR( IF(AND(ISNUMBER(SEARCH("1:1", A7)), ISNUMBER(SEARCH("Desk", A7))), "1:1 Desk", IF(AND(ISNUMBER(SEARCH("1:1", A7)), ISNUMBER(SEARCH("Mob", A7))), "1:1 Mob", IF(AND(ISNUMBER(SEARCH("Exact", A7)), ISNUMBER(SEARCH("Desk", A7))), "Exact Desk", IF(AND(ISNUMBER(SEARCH("Exact", A7)), ISNUMBER(SEARCH("Mob", A7))), "Exact Mob", IF(AND(ISNUMBER(SEARCH("Phrase", A7)), ISNUMBER(SEARCH("Desk", A7))), "Phrase Desk", IF(AND(ISNUMBER(SEARCH("Phrase", A7)), ISNUMBER(SEARCH("Mob", A7))), "Phrase Mob", "Other")))))), "Other") -> 1:1 Mob
A8: Shop - 1:1 - Mob - [shop coupon] | B8: July | C8: 152394 | D8: 59177 | E8: 0.39 | F8: 2666 | G8: 0.04 | H8: 19371 | I8: 0.33 | J8: 13699 | K8: 294536.92 | L8: -5672.271 | M8: =IFERROR( IF(AND(ISNUMBER(SEARCH("1:1", A8)), ISNUMBER(SEARCH("Desk", A8))), "1:1 Desk", IF(AND(ISNUMBER(SEARCH("1:1", A8)), ISNUMBER(SEARCH("Mob", A8))), "1:1 Mob", IF(AND(ISNUMBER(SEARCH("Exact", A8)), ISNUMBER(SEARCH("Desk", A8))), "Exact Desk", IF(AND(ISNUMBER(SEARCH("Exact", A8)), ISNUMBER(SEARCH("Mob", A8))), "Exact Mob", IF(AND(ISNUMBER(SEARCH("Phrase", A8)), ISNUMBER(SEARCH("Desk", A8))), "Phrase Desk", IF(AND(ISNUMBER(SEARCH("Phrase", A8)), ISNUMBER(SEARCH("Mob", A8))), "Phrase Mob", "Other")))))), "Other") -> 1:1 Mob
A9: Shop - 1:1 - Mob - [shop discount code] | B9: July | C9: 9950 | D9: 4283 | E9: 0.43 | F9: 347 | G9: 0.05 | H9: 2637 | I9: 0.62 | J9: 2038 | K9: 46026.32 | L9: -598.993 | M9: =IFERROR( IF(AND(ISNUMBER(SEARCH("1:1", A9)), ISNUMBER(SEARCH("Desk", A9))), "1:1 Desk", IF(AND(ISNUMBER(SEARCH("1:1", A9)), ISNUMBER(SEARCH("Mob", A9))), "1:1 Mob", IF(AND(ISNUMBER(SEARCH("Exact", A9)), ISNUMBER(SEARCH("Desk", A9))), "Exact Desk", IF(AND(ISNUMBER(SEARCH("Exact", A9)), ISNUMBER(SEARCH("Mob", A9))), "Exact Mob", IF(AND(ISNUMBER(SEARCH("Phrase", A9)), ISNUMBER(SEARCH("Desk", A9))), "Phrase Desk", IF(AND(ISNUMBER(SEARCH("Phrase", A9)), ISNUMBER(SEARCH("Mob", A9))), "Phrase Mob", "Other")))))), "Other") -> 1:1 Mob
A10: Shop - 1:1 - Mob - [shop promo code] | B10: July | C10: 57373 | D10: 27121 | E10: 0.47 | F10: 2940 | G10: 0.07 | H10: 16946 | I10: 0.62 | J10: 14565 | K10: 321387.88 | L10: -2380.616 | M10: =IFERROR( IF(AND(ISNUMBER(SEARCH("1:1", A10)), ISNUMBER(SEARCH("Desk", A10))), "1:1 Desk", IF(AND(ISNUMBER(SEARCH("1:1", A10)), ISNUMBER(SEARCH("Mob", A10))), "1:1 Mob", IF(AND(ISNUMBER(SEARCH("Exact", A10)), ISNUMBER(SEARCH("Desk", A10))), "Exact Desk", IF(AND(ISNUMBER(SEARCH("Exact", A10)), ISNUMBER(SEARCH("Mob", A10))), "Exact Mob", IF(AND(ISNUMBER(SEARCH("Phrase", A10)), ISNUMBER(SEARCH("Desk", A10))), "Phrase Desk", IF(AND(ISNUMBER(SEARCH("Phrase", A10)), ISNUMBER(SEARCH("Mob", A10))), "Phrase Mob", "Other")))))), "Other") -> 1:1 Mob
A11: Shop - 1:1 - Mob - [shop promo] | B11: July | C11: 1875 | D11: 706 | E11: 0.38 | F11: 69 | G11: 0.07 | H11: 485 | I11: 0.69 | J11: 409 | K11: 8946.99 | L11: -75.734 | M11: =IFERROR( IF(AND(ISNUMBER(SEARCH("1:1", A11)), ISNUMBER(SEARCH("Desk", A11))), "1:1 Desk", IF(AND(ISNUMBER(SEARCH("1:1", A11)), ISNUMBER(SEARCH("Mob", A11))), "1:1 Mob", IF(AND(ISNUMBER(SEARCH("Exact", A11)), ISNUMBER(SEARCH("Desk", A11))), "Exact Desk", IF(AND(ISNUMBER(SEARCH("Exact", A11)), ISNUMBER(SEARCH("Mob", A11))), "Exact Mob", IF(AND(ISNUMBER(SEARCH("Phrase", A11)), ISNUMBER(SEARCH("Desk", A11))), "Phrase Desk", IF(AND(ISNUMBER(SEARCH("Phrase", A11)), ISNUMBER(SEARCH("Mob", A11))), "Phrase Mob", "Other")))))), "Other") -> 1:1 Mob
A12: Shop - Exact - Desk - Competitor | B12: July | C12: 721 | D12: 195 | E12: 0.27 | F12: 25 | G12: 0.09 | H12: 188 | I12: 0.97 | J12: 188 | K12: 3853.27 | L12: 0.184 | M12: =IFERROR( IF(AND(ISNUMBER(SEARCH("1:1", A12)), ISNUMBER(SEARCH("Desk", A12))), "1:1 Desk", IF(AND(ISNUMBER(SEARCH("1:1", A12)), ISNUMBER(SEARCH("Mob", A12))), "1:1 Mob", IF(AND(ISNUMBER(SEARCH("Exact", A12)), ISNUMBER(SEARCH("Desk", A12))), "Exact Desk", IF(AND(ISNUMBER(SEARCH("Exact", A12)), ISNUMBER(SEARCH("Mob", A12))), "Exact Mob", IF(AND(ISNUMBER(SEARCH("Phrase", A12)), ISNUMBER(SEARCH("Desk", A12))), "Phrase Desk", IF(AND(ISNUMBER(SEARCH("Phrase", A12)), ISNUMBER(SEARCH("Mob", A12))), "Phrase Mob", "Other")))))), "Other") -> Exact Desk
A13: Shop - Exact - Desk - Coupon Code | B13: July | C13: 8053 | D13: 2678 | E13: 0.33 | F13: 392 | G13: 0.08 | H13: 2814 | I13: 1.05 | J13: 2475 | K13: 56017.16 | L13: -338.63 | M13: =IFERROR( IF(AND(ISNUMBER(SEARCH("1:1", A13)), ISNUMBER(SEARCH("Desk", A13))), "1:1 Desk", IF(AND(ISNUMBER(SEARCH("1:1", A13)), ISNUMBER(SEARCH("Mob", A13))), "1:1 Mob", IF(AND(ISNUMBER(SEARCH("Exact", A13)), ISNUMBER(SEARCH("Desk", A13))), "Exact Desk", IF(AND(ISNUMBER(SEARCH("Exact", A13)), ISNUMBER(SEARCH("Mob", A13))), "Exact Mob", IF(AND(ISNUMBER(SEARCH("Phrase", A13)), ISNUMBER(SEARCH("Desk", A13))), "Phrase Desk", IF(AND(ISNUMBER(SEARCH("Phrase", A13)), ISNUMBER(SEARCH("Mob", A13))), "Phrase Mob", "Other")))))), "Other") -> Exact Desk
... A191: Shop - Exact - Desk - Promo Code | B191: November | C191: 25592 | D191: 7726 | E191: 0.3 | F191: 1731 | G191: 0.14 | H191: 10914 | I191: 1.41 | J191: 11223 | K191: 236665.59 | L191: 308.975 | M191: =IFERROR( IF(AND(ISNUMBER(SEARCH("1:1", A191)), ISNUMBER(SEARCH("Desk", A191))), "1:1 Desk", IF(AND(ISNUMBER(SEARCH("1:1", A191)), ISNUMBER(SEARCH("Mob", A191))), "1:1 Mob", IF(AND(ISNUMBER(SEARCH("Exact", A191)), ISNUMBER(SEARCH("Desk", A191))), "Exact Desk", IF(AND(ISNUMBER(SEARCH("Exact", A191)), ISNUMBER(SEARCH("Mob", A191))), "Exact Mob", IF(AND(ISNUMBER(SEARCH("Phrase", A191)), ISNUMBER(SEARCH("Desk", A191))), "Phrase Desk", IF(AND(ISNUMBER(SEARCH("Phrase", A191)), ISNUMBER(SEARCH("Mob", A191))), "Phrase Mob", "Other")))))), "Other") -> Exact Desk
